odoo8_addon_website_sale_checkout_country_vat-8.0.1.0.0.99.dev3-py2.7-nspkg.pth
odoo_addons/website_sale_checkout_country_vat/__openerp__.py
odoo_addons/website_sale_checkout_country_vat/__init__.py
odoo_addons/website_sale_checkout_country_vat/README.rst
odoo_addons/website_sale_checkout_country_vat/i18n/es.po
odoo_addons/website_sale_checkout_country_vat/views/assets.xml
odoo_addons/website_sale_checkout_country_vat/views/templates.xml
odoo_addons/website_sale_checkout_country_vat/static/description/icon.png
odoo_addons/website_sale_checkout_country_vat/static/src/js/change_country.js
odoo8_addon_website_sale_checkout_country_vat-8.0.1.0.0.99.dev3.dist-info/top_level.txt
odoo8_addon_website_sale_checkout_country_vat-8.0.1.0.0.99.dev3.dist-info/WHEEL
odoo8_addon_website_sale_checkout_country_vat-8.0.1.0.0.99.dev3.dist-info/RECORD
odoo8_addon_website_sale_checkout_country_vat-8.0.1.0.0.99.dev3.dist-info/metadata.json
odoo8_addon_website_sale_checkout_country_vat-8.0.1.0.0.99.dev3.dist-info/DESCRIPTION.rst
odoo8_addon_website_sale_checkout_country_vat-8.0.1.0.0.99.dev3.dist-info/METADATA
odoo8_addon_website_sale_checkout_country_vat-8.0.1.0.0.99.dev3.dist-info/namespace_packages.txt
