Metadata-Version: 2.0
Name: odoo8-addon-website-sale-checkout-country-vat
Version: 8.0.1.0.0.99.dev3
Summary: Autocomplete VAT in checkout process
Home-page: http://www.tecnativa.com
Author: Tecnativa, Odoo Community Association (OCA)
Author-email: support@odoo-community.org
License: LGPL-3
Platform: UNKNOWN
Requires-Dist: odoo (<9.0a,>=8.0a)
Requires-Dist: odoo8-addon-website-snippet-country-dropdown
Classifier: Programming Language :: Python :: 2.7
Classifier: Framework :: Odoo
Classifier: License :: OSI Approved :: GNU Lesser General Public License v3 (LGPLv3)
